notegame/__init__.py
notegame/games/__init__.py
notegame/games/nonogram/__init__.py
notegame/games/nonogram/main.py
notegame/games/nonogram/reader.py
notegame/games/nonogram/core/__init__.py
notegame/games/nonogram/core/backtracking.py
notegame/games/nonogram/core/board.py
notegame/games/nonogram/core/color.py
notegame/games/nonogram/core/common.py
notegame/games/nonogram/core/propagation.py
notegame/games/nonogram/core/renderer.py
notegame/games/nonogram/example/__init__.py
notegame/games/nonogram/example/core.py
notegame/games/nonogram/solver/__init__.py
notegame/games/nonogram/solver/base.py
notegame/games/nonogram/solver/bgu.py
notegame/games/nonogram/solver/efficient.py
notegame/games/nonogram/solver/machine.py
notegame/games/nonogram/solver/simpson.py
notegame/games/nonogram/utils/__init__.py
notegame/games/nonogram/utils/cache.py
notegame/games/nonogram/utils/fsm.py
notegame/games/nonogram/utils/iter.py
notegame/games/nonogram/utils/other.py
notegame/games/nonogram/utils/priority_dict.py
notegame/games/sudoku/__init__.py
notegame/games/sudoku/core.py
notegame/games/topwar/__init__.py
notegame/games/topwar/main.py
notegame/games/topwar/test.py
notegame/games/topwar/action/__init__.py
notegame/games/topwar/action/core.py
notegame/games/topwar/core/__init__.py
notegame/games/topwar/core/db.py
notegame/games/topwar/entity/__init__.py
notegame/games/topwar/entity/base.py
notegame/games/topwar/entity/base_enum.py
notegame/games/topwar/entity/core.py
notegame/games/topwar/entity/request.py
notegame/games/topwar/entity/response.py
notegame/games/topwar/jobs/__init__.py
notegame/games/topwar/jobs/gift_code.py
notegame/games/topwar/server/__init__.py
notegame/games/topwar/server/action.py
notegame/games/topwar/server/job.py
notegame/games/topwar/server/message.py
notegame/games/topwar/utils/__init__.py
notegame/games/topwar/utils/core.py
notegame/shumo/__init__.py
notegame/shumo/entity.py
notegame/shumo/load_data.py
notegame/shumo/model.py
notegame/shumo/solution.py
notegame-0.5.18.dist-info/LICENSE
notegame-0.5.18.dist-info/METADATA
notegame-0.5.18.dist-info/WHEEL
notegame-0.5.18.dist-info/top_level.txt
notegame-0.5.18.dist-info/RECORD
