Metadata-Version: 2.1
Name: notegame
Version: 0.5.18
Summary: notegame
Home-page: https://github.com/1007530194
Author: bingtao
Author-email: 1007530194@qq.com
License: UNKNOWN
Platform: UNKNOWN
Requires-Dist: tqdm
